duablo/__about__.py
duablo/__init__.py
duablo/__main__.py
duablo-0.1.0.dist-info/METADATA
duablo-0.1.0.dist-info/WHEEL
duablo-0.1.0.dist-info/entry_points.txt
duablo-0.1.0.dist-info/licenses/LICENSE
duablo-0.1.0.dist-info/RECORD
